README.md
setup.cfg
setup.py
egida/__init__.py
egida/egida.py
egida.egg-info/PKG-INFO
egida.egg-info/SOURCES.txt
egida.egg-info/dependency_links.txt
egida.egg-info/entry_points.txt
egida.egg-info/requires.txt
egida.egg-info/top_level.txt
egida/common/__init__.py
egida/common/command.py
egida/common/file_manager.py
egida/common/hosts
egida/common/playbook-custom.yml
egida/common/playbook.py
egida/common/playbook.yml.j2
egida/config/__init__.py
egida/custom/__init__.py
egida/custom/vars_template.yml
egida/dsl/__init__.py
egida/dsl/codegen/__init__.py
egida/dsl/codegen/aspida.py
egida/dsl/codegen/vars_visitor.py
egida/dsl/listeners/__init__.py
egida/dsl/listeners/aspida_listener.py
egida/dsl/listeners/error_listener.py
egida/dsl/parser/__init__.py
egida/dsl/parser/aspida_lexer.py
egida/dsl/parser/aspida_parser.py
egida/dsl/visitor/__init__.py
egida/dsl/visitor/aspida_visitor.py
egida/info/__init__.py
egida/info/worker_api_client.py
egida/menu/__init__.py
egida/menu/console.py
egida/menu/cis/__init__.py
egida/menu/cis/all.py
egida/menu/cis/controls.py
egida/menu/cis/points.py
egida/menu/cis/sections.py