Metadata-Version: 2.1
Name: egida
Version: 1.0.1
Summary: Egida Project Main
Home-page: https://antonioalfa22.github.io/egida/
Author: Antonio Paya Gonzalez
Author-email: antoniopaya@outlook.com
License: MIT
Download-URL: https://github.com/antonioalfa22/egida/releases/tag/1.0.1
Platform: UNKNOWN
